{
  "metadata": {
    "timed": true,
    "story ID": "03be0cd3-b1cf-441e-b74f-7d7a9f6334aa",
    "title": {
      "_default": "Soopa de liima"
    },
    "media": {
      "audio": "https://cds.library.brown.edu/projects/yucatec/LingView/data/media_files/Soopa de liima.wav",
      "video": "https://cds.library.brown.edu/projects/yucatec/LingView/data/media_files/Soopa de liima.mp4"
    },
    "languages": [],
    "date_created": "",
    "date_uploaded": "5/20/2020",
    "source": {
      "_default": ""
    },
    "description": "",
    "genre": "",
    "author": "",
    "glosser": "",
    "speakers": [
      "[APELLIDO, NOMBRE]"
    ],
    "xml_file_name": "Soopa de liima.eaf",
    "source_filetype": "ELAN",
    "tier IDs": {
      "T1": {
        "name": "H1_Transcripción",
        "subdivided": false
      },
      "T2": {
        "name": "H1_Maya",
        "subdivided": false
      },
      "T3": {
        "name": "H1_Traducción",
        "subdivided": false
      }
    },
    "speaker IDs": {
      "S1": {
        "name": "[APELLIDO, NOMBRE]",
        "tier": "T1"
      }
    }
  },
  "sentences": [
    {
      "speaker": "S1",
      "tier": "T1",
      "start_time_ms": 1445,
      "end_time_ms": 3020,
      "num_slots": 1,
      "text": "Tene' in k'aabae'  Roberta.",
      "dependents": [
        {
          "tier": "T2",
          "values": [
            {
              "start_slot": 0,
              "end_slot": 1,
              "value": "Tene' in k'aabae'  Roberta."
            }
          ]
        },
        {
          "tier": "T3",
          "values": [
            {
              "start_slot": 0,
              "end_slot": 1,
              "value": "Yo me llamo Robertha."
            }
          ]
        }
      ]
    },
    {
      "speaker": "S1",
      "tier": "T1",
      "start_time_ms": 3540,
      "end_time_ms": 5405,
      "num_slots": 1,
      "text": "berae' nuke'en in eksplikaarte'ex",
      "dependents": [
        {
          "tier": "T2",
          "values": [
            {
              "start_slot": 0,
              "end_slot": 1,
              "value": "beorae' nuka'ajen in eksplikaarte'ex"
            }
          ]
        },
        {
          "tier": "T3",
          "values": [
            {
              "start_slot": 0,
              "end_slot": 1,
              "value": "ahora les voy a explicar "
            }
          ]
        }
      ]
    },
    {
      "speaker": "S1",
      "tier": "T1",
      "start_time_ms": 5440,
      "end_time_ms": 6235,
      "num_slots": 1,
      "text": "bix uchin kanik",
      "dependents": [
        {
          "tier": "T2",
          "values": [
            {
              "start_slot": 0,
              "end_slot": 1,
              "value": "bix uch in kanik"
            }
          ]
        },
        {
          "tier": "T3",
          "values": [
            {
              "start_slot": 0,
              "end_slot": 1,
              "value": "cómo aprendí"
            }
          ]
        }
      ]
    },
    {
      "speaker": "S1",
      "tier": "T1",
      "start_time_ms": 6560,
      "end_time_ms": 8225,
      "num_slots": 1,
      "text": "in máak'a'ante soopa de liimao'.",
      "dependents": [
        {
          "tier": "T2",
          "values": [
            {
              "start_slot": 0,
              "end_slot": 1,
              "value": "in máak'a'ante soopa de liimao'."
            }
          ]
        },
        {
          "tier": "T3",
          "values": [
            {
              "start_slot": 0,
              "end_slot": 1,
              "value": "a preparar la sopa de lima."
            }
          ]
        }
      ]
    },
    {
      "speaker": "S1",
      "tier": "T1",
      "start_time_ms": 8885,
      "end_time_ms": 11355,
      "num_slots": 1,
      "text": "tene' uch kin kanik in máak'a'ant le soopa de liimao'",
      "dependents": [
        {
          "tier": "T2",
          "values": [
            {
              "start_slot": 0,
              "end_slot": 1,
              "value": "Tene' uch kin kanik in máak'ant le soopa de liimao'"
            }
          ]
        },
        {
          "tier": "T3",
          "values": [
            {
              "start_slot": 0,
              "end_slot": 1,
              "value": "Yo aprendí a preparar la sopa de lima cuando"
            }
          ]
        }
      ]
    },
    {
      "speaker": "S1",
      "tier": "T1",
      "start_time_ms": 11395,
      "end_time_ms": 12700,
      "num_slots": 1,
      "text": "ooken meyaj ti' up'ée...",
      "dependents": [
        {
          "tier": "T2",
          "values": [
            {
              "start_slot": 0,
              "end_slot": 1,
              "value": "ooken meyaj ti' jump'éel..."
            }
          ]
        },
        {
          "tier": "T3",
          "values": [
            {
              "start_slot": 0,
              "end_slot": 1,
              "value": "entre a trabajar en un..."
            }
          ]
        }
      ]
    },
    {
      "speaker": "S1",
      "tier": "T1",
      "start_time_ms": 13160,
      "end_time_ms": 14845,
      "num_slots": 1,
      "text": "ti' up'ée restawraan,",
      "dependents": [
        {
          "tier": "T2",
          "values": [
            {
              "start_slot": 0,
              "end_slot": 1,
              "value": "ti' jump'éel restawraan."
            }
          ]
        },
        {
          "tier": "T3",
          "values": [
            {
              "start_slot": 0,
              "end_slot": 1,
              "value": "en un restaurante,"
            }
          ]
        }
      ]
    },
    {
      "speaker": "S1",
      "tier": "T1",
      "start_time_ms": 15065,
      "end_time_ms": 17355,
      "num_slots": 1,
      "text": "ookene' chéen de ayudaantei",
      "dependents": [
        {
          "tier": "T2",
          "values": [
            {
              "start_slot": 0,
              "end_slot": 1,
              "value": "ookene' chéen de ayudaantei"
            }
          ]
        },
        {
          "tier": "T3",
          "values": [
            {
              "start_slot": 0,
              "end_slot": 1,
              "value": "entre solo de ayudante"
            }
          ]
        }
      ]
    },
    {
      "speaker": "S1",
      "tier": "T1",
      "start_time_ms": 17920,
      "end_time_ms": 18600,
      "num_slots": 1,
      "text": "pero tene'",
      "dependents": [
        {
          "tier": "T2",
          "values": [
            {
              "start_slot": 0,
              "end_slot": 1,
              "value": "pero tene'"
            }
          ]
        },
        {
          "tier": "T3",
          "values": [
            {
              "start_slot": 0,
              "end_slot": 1,
              "value": "pero a mí"
            }
          ]
        }
      ]
    },
    {
      "speaker": "S1",
      "tier": "T1",
      "start_time_ms": 18617,
      "end_time_ms": 19952,
      "num_slots": 1,
      "text": "uts tin wichin kanku jee",
      "dependents": [
        {
          "tier": "T2",
          "values": [
            {
              "start_slot": 0,
              "end_slot": 1,
              "value": "uts tin wich in kanik u jeel"
            }
          ]
        },
        {
          "tier": "T3",
          "values": [
            {
              "start_slot": 0,
              "end_slot": 1,
              "value": "me gusta aprender otras"
            }
          ]
        }
      ]
    },
    {
      "speaker": "S1",
      "tier": "T1",
      "start_time_ms": 20029,
      "end_time_ms": 21719,
      "num_slots": 1,
      "text": "e in máak'anke ki'iwaj beyo',",
      "dependents": [
        {
          "tier": "T2",
          "values": [
            {
              "start_slot": 0,
              "end_slot": 1,
              "value": "le in máak'antik le ki'iwaj beyo',"
            }
          ]
        },
        {
          "tier": "T3",
          "values": [
            {
              "start_slot": 0,
              "end_slot": 1,
              "value": "de preparar la comida así,"
            }
          ]
        }
      ]
    },
    {
      "speaker": "S1",
      "tier": "T1",
      "start_time_ms": 22240,
      "end_time_ms": 24400,
      "num_slots": 1,
      "text": "tene' chéen kin wik bix u máak'anta'ale'",
      "dependents": [
        {
          "tier": "T2",
          "values": [
            {
              "start_slot": 0,
              "end_slot": 1,
              "value": "tene' chéen kin wilik bix u máak'anta'ale'"
            }
          ]
        },
        {
          "tier": "T3",
          "values": [
            {
              "start_slot": 0,
              "end_slot": 1,
              "value": "yo solo veía cómo se preparaba "
            }
          ]
        }
      ]
    },
    {
      "speaker": "S1",
      "tier": "T1",
      "start_time_ms": 24970,
      "end_time_ms": 25690,
      "num_slots": 1,
      "text": "ka tin kanaj,",
      "dependents": [
        {
          "tier": "T2",
          "values": [
            {
              "start_slot": 0,
              "end_slot": 1,
              "value": "ka tin kanaj,"
            }
          ]
        },
        {
          "tier": "T3",
          "values": [
            {
              "start_slot": 0,
              "end_slot": 1,
              "value": "y lo aprendí,"
            }
          ]
        }
      ]
    },
    {
      "speaker": "S1",
      "tier": "T1",
      "start_time_ms": 27060,
      "end_time_ms": 28450,
      "num_slots": 1,
      "text": "ka tin kanaj in máak'antej,",
      "dependents": [
        {
          "tier": "T2",
          "values": [
            {
              "start_slot": 0,
              "end_slot": 1,
              "value": "ka tin kanaj in máak'antej,"
            }
          ]
        },
        {
          "tier": "T3",
          "values": [
            {
              "start_slot": 0,
              "end_slot": 1,
              "value": "y lo aprendí a preparar,"
            }
          ]
        }
      ]
    },
    {
      "speaker": "S1",
      "tier": "T1",
      "start_time_ms": 28850,
      "end_time_ms": 29590,
      "num_slots": 1,
      "text": "despweese'",
      "dependents": [
        {
          "tier": "T2",
          "values": [
            {
              "start_slot": 0,
              "end_slot": 1,
              "value": "despweese'"
            }
          ]
        },
        {
          "tier": "T3",
          "values": [
            {
              "start_slot": 0,
              "end_slot": 1,
              "value": "después"
            }
          ]
        }
      ]
    },
    {
      "speaker": "S1",
      "tier": "T1",
      "start_time_ms": 29595,
      "end_time_ms": 31435,
      "num_slots": 1,
      "text": "ka tin beetaj tin naay in jaanti'.",
      "dependents": [
        {
          "tier": "T2",
          "values": [
            {
              "start_slot": 0,
              "end_slot": 1,
              "value": "ka tin beetaj tin naay in jaanti'."
            }
          ]
        },
        {
          "tier": "T3",
          "values": [
            {
              "start_slot": 0,
              "end_slot": 1,
              "value": "preparé para comer en mi casa."
            }
          ]
        }
      ]
    },
    {
      "speaker": "S1",
      "tier": "T1",
      "start_time_ms": 32280,
      "end_time_ms": 33755,
      "num_slots": 1,
      "text": "E soopa de liimao'",
      "dependents": [
        {
          "tier": "T2",
          "values": [
            {
              "start_slot": 0,
              "end_slot": 1,
              "value": "Le soopa de liimao'"
            }
          ]
        },
        {
          "tier": "T3",
          "values": [
            {
              "start_slot": 0,
              "end_slot": 1,
              "value": "La sopa de lima "
            }
          ]
        }
      ]
    },
    {
      "speaker": "S1",
      "tier": "T1",
      "start_time_ms": 33792,
      "end_time_ms": 34867,
      "num_slots": 1,
      "text": "chéen ba'ax ku biske'",
      "dependents": [
        {
          "tier": "T2",
          "values": [
            {
              "start_slot": 0,
              "end_slot": 1,
              "value": "chéen ba'ax ku bisike'"
            }
          ]
        },
        {
          "tier": "T3",
          "values": [
            {
              "start_slot": 0,
              "end_slot": 1,
              "value": "solamente lleva"
            }
          ]
        }
      ]
    },
    {
      "speaker": "S1",
      "tier": "T1",
      "start_time_ms": 35970,
      "end_time_ms": 37700,
      "num_slots": 1,
      "text": "chéen yéetej kaax,",
      "dependents": [
        {
          "tier": "T2",
          "values": [
            {
              "start_slot": 0,
              "end_slot": 1,
              "value": "chéen yéetel jkaax,"
            }
          ]
        },
        {
          "tier": "T3",
          "values": [
            {
              "start_slot": 0,
              "end_slot": 1,
              "value": "solo con pollo,"
            }
          ]
        }
      ]
    },
    {
      "speaker": "S1",
      "tier": "T1",
      "start_time_ms": 38410,
      "end_time_ms": 39250,
      "num_slots": 1,
      "text": "moron,",
      "dependents": [
        {
          "tier": "T2",
          "values": [
            {
              "start_slot": 0,
              "end_slot": 1,
              "value": "moron,"
            }
          ]
        },
        {
          "tier": "T3",
          "values": [
            {
              "start_slot": 0,
              "end_slot": 1,
              "value": "morrón,"
            }
          ]
        }
      ]
    },
    {
      "speaker": "S1",
      "tier": "T1",
      "start_time_ms": 39885,
      "end_time_ms": 41215,
      "num_slots": 1,
      "text": "p'aak yéete seboyáaj",
      "dependents": [
        {
          "tier": "T2",
          "values": [
            {
              "start_slot": 0,
              "end_slot": 1,
              "value": "p'aak yéetel seboyáaj"
            }
          ]
        },
        {
          "tier": "T3",
          "values": [
            {
              "start_slot": 0,
              "end_slot": 1,
              "value": "tomate con cebolla"
            }
          ]
        }
      ]
    },
    {
      "speaker": "S1",
      "tier": "T1",
      "start_time_ms": 42250,
      "end_time_ms": 43405,
      "num_slots": 1,
      "text": "yéetel le kóonsomejo'",
      "dependents": [
        {
          "tier": "T2",
          "values": [
            {
              "start_slot": 0,
              "end_slot": 1,
              "value": "yéetel le kóonsomejo'"
            }
          ]
        },
        {
          "tier": "T3",
          "values": [
            {
              "start_slot": 0,
              "end_slot": 1,
              "value": "y el consomé"
            }
          ]
        }
      ]
    },
    {
      "speaker": "S1",
      "tier": "T1",
      "start_time_ms": 43845,
      "end_time_ms": 46010,
      "num_slots": 1,
      "text": "yéetele u... u oojai lawrel",
      "dependents": [
        {
          "tier": "T2",
          "values": [
            {
              "start_slot": 0,
              "end_slot": 1,
              "value": "yéetel le u... u oojai lawrel"
            }
          ]
        },
        {
          "tier": "T3",
          "values": [
            {
              "start_slot": 0,
              "end_slot": 1,
              "value": "y la... la hoja del lawrel"
            }
          ]
        }
      ]
    },
    {
      "speaker": "S1",
      "tier": "T1",
      "start_time_ms": 47390,
      "end_time_ms": 48105,
      "num_slots": 1,
      "text": "em...",
      "dependents": [
        {
          "tier": "T2",
          "values": [
            {
              "start_slot": 0,
              "end_slot": 1,
              "value": "em..."
            }
          ]
        },
        {
          "tier": "T3",
          "values": [
            {
              "start_slot": 0,
              "end_slot": 1,
              "value": "em..."
            }
          ]
        }
      ]
    },
    {
      "speaker": "S1",
      "tier": "T1",
      "start_time_ms": 50040,
      "end_time_ms": 51000,
      "num_slots": 1,
      "text": "yéetele e...",
      "dependents": [
        {
          "tier": "T2",
          "values": [
            {
              "start_slot": 0,
              "end_slot": 1,
              "value": "yéetel le le..."
            }
          ]
        },
        {
          "tier": "T3",
          "values": [
            {
              "start_slot": 0,
              "end_slot": 1,
              "value": "y la la..."
            }
          ]
        }
      ]
    },
    {
      "speaker": "S1",
      "tier": "T1",
      "start_time_ms": 51175,
      "end_time_ms": 51970,
      "num_slots": 1,
      "text": "e liimao'.",
      "dependents": [
        {
          "tier": "T2",
          "values": [
            {
              "start_slot": 0,
              "end_slot": 1,
              "value": "le liimao'."
            }
          ]
        },
        {
          "tier": "T3",
          "values": [
            {
              "start_slot": 0,
              "end_slot": 1,
              "value": "la lima."
            }
          ]
        }
      ]
    },
    {
      "speaker": "S1",
      "tier": "T1",
      "start_time_ms": 54930,
      "end_time_ms": 55875,
      "num_slots": 1,
      "text": "Eesten...",
      "dependents": [
        {
          "tier": "T2",
          "values": [
            {
              "start_slot": 0,
              "end_slot": 1,
              "value": "Eesten..."
            }
          ]
        },
        {
          "tier": "T3",
          "values": [
            {
              "start_slot": 0,
              "end_slot": 1,
              "value": "Esten..."
            }
          ]
        }
      ]
    },
    {
      "speaker": "S1",
      "tier": "T1",
      "start_time_ms": 56065,
      "end_time_ms": 57150,
      "num_slots": 1,
      "text": "ti'ala máak'anke'",
      "dependents": [
        {
          "tier": "T2",
          "values": [
            {
              "start_slot": 0,
              "end_slot": 1,
              "value": "ti'al a máak'antike'"
            }
          ]
        },
        {
          "tier": "T3",
          "values": [
            {
              "start_slot": 0,
              "end_slot": 1,
              "value": "para que lo prepares"
            }
          ]
        }
      ]
    },
    {
      "speaker": "S1",
      "tier": "T1",
      "start_time_ms": 58820,
      "end_time_ms": 59160,
      "num_slots": 1,
      "text": "e...",
      "dependents": [
        {
          "tier": "T2",
          "values": [
            {
              "start_slot": 0,
              "end_slot": 1,
              "value": "e..."
            }
          ]
        },
        {
          "tier": "T3",
          "values": [
            {
              "start_slot": 0,
              "end_slot": 1,
              "value": "eh..."
            }
          ]
        }
      ]
    },
    {
      "speaker": "S1",
      "tier": "T1",
      "start_time_ms": 59915,
      "end_time_ms": 60805,
      "num_slots": 1,
      "text": "ej kaaxo'",
      "dependents": [
        {
          "tier": "T2",
          "values": [
            {
              "start_slot": 0,
              "end_slot": 1,
              "value": "le jkaaxo'"
            }
          ]
        },
        {
          "tier": "T3",
          "values": [
            {
              "start_slot": 0,
              "end_slot": 1,
              "value": "el pollo"
            }
          ]
        }
      ]
    },
    {
      "speaker": "S1",
      "tier": "T1",
      "start_time_ms": 60830,
      "end_time_ms": 61790,
      "num_slots": 1,
      "text": "yana p'o'ik,",
      "dependents": [
        {
          "tier": "T2",
          "values": [
            {
              "start_slot": 0,
              "end_slot": 1,
              "value": "yaan a p'o'ik,"
            }
          ]
        },
        {
          "tier": "T3",
          "values": [
            {
              "start_slot": 0,
              "end_slot": 1,
              "value": "lo vas a lavar,"
            }
          ]
        }
      ]
    },
    {
      "speaker": "S1",
      "tier": "T1",
      "start_time_ms": 61880,
      "end_time_ms": 62755,
      "num_slots": 1,
      "text": "chéen ts'oojka p'o'ke'",
      "dependents": [
        {
          "tier": "T2",
          "values": [
            {
              "start_slot": 0,
              "end_slot": 1,
              "value": "chéen ts'o'okok a p'o'ike'"
            }
          ]
        },
        {
          "tier": "T3",
          "values": [
            {
              "start_slot": 0,
              "end_slot": 1,
              "value": "cuando termines de lavarlo"
            }
          ]
        }
      ]
    },
    {
      "speaker": "S1",
      "tier": "T1",
      "start_time_ms": 62847,
      "end_time_ms": 63702,
      "num_slots": 1,
      "text": "ka ts'áaik te' k'áak'o'",
      "dependents": [
        {
          "tier": "T2",
          "values": [
            {
              "start_slot": 0,
              "end_slot": 1,
              "value": "ka ts'áaik te' k'áak'o'"
            }
          ]
        },
        {
          "tier": "T3",
          "values": [
            {
              "start_slot": 0,
              "end_slot": 1,
              "value": "lo pones en el fuego"
            }
          ]
        }
      ]
    },
    {
      "speaker": "S1",
      "tier": "T1",
      "start_time_ms": 63760,
      "end_time_ms": 65165,
      "num_slots": 1,
      "text": "yéete táanchumuk u ja'ij",
      "dependents": [
        {
          "tier": "T2",
          "values": [
            {
              "start_slot": 0,
              "end_slot": 1,
              "value": "yéetel táanchumuk u ja'ij"
            }
          ]
        },
        {
          "tier": "T3",
          "values": [
            {
              "start_slot": 0,
              "end_slot": 1,
              "value": "con la mitad del agua"
            }
          ]
        }
      ]
    },
    {
      "speaker": "S1",
      "tier": "T1",
      "start_time_ms": 65257,
      "end_time_ms": 65917,
      "num_slots": 1,
      "text": "te' ooyao'.",
      "dependents": [
        {
          "tier": "T2",
          "values": [
            {
              "start_slot": 0,
              "end_slot": 1,
              "value": "te' ooyao'."
            }
          ]
        },
        {
          "tier": "T3",
          "values": [
            {
              "start_slot": 0,
              "end_slot": 1,
              "value": "en la olla."
            }
          ]
        }
      ]
    },
    {
      "speaker": "S1",
      "tier": "T1",
      "start_time_ms": 67330,
      "end_time_ms": 68050,
      "num_slots": 1,
      "text": "Chéen ts'o'ojke'",
      "dependents": [
        {
          "tier": "T2",
          "values": [
            {
              "start_slot": 0,
              "end_slot": 1,
              "value": "chéen ts'o'ojke'"
            }
          ]
        },
        {
          "tier": "T3",
          "values": [
            {
              "start_slot": 0,
              "end_slot": 1,
              "value": "Después"
            }
          ]
        }
      ]
    },
    {
      "speaker": "S1",
      "tier": "T1",
      "start_time_ms": 69060,
      "end_time_ms": 69595,
      "num_slots": 1,
      "text": "ka...",
      "dependents": [
        {
          "tier": "T2",
          "values": [
            {
              "start_slot": 0,
              "end_slot": 1,
              "value": "ka..."
            }
          ]
        },
        {
          "tier": "T3",
          "values": [
            {
              "start_slot": 0,
              "end_slot": 1,
              "value": "lo..."
            }
          ]
        }
      ]
    },
    {
      "speaker": "S1",
      "tier": "T1",
      "start_time_ms": 72050,
      "end_time_ms": 73175,
      "num_slots": 1,
      "text": "ka ts'áaik te' k'áak' beyo'",
      "dependents": [
        {
          "tier": "T2",
          "values": [
            {
              "start_slot": 0,
              "end_slot": 1,
              "value": "ka ts'áaik te' k'áak' beyo'"
            }
          ]
        },
        {
          "tier": "T3",
          "values": [
            {
              "start_slot": 0,
              "end_slot": 1,
              "value": "lo pones en la candela así"
            }
          ]
        }
      ]
    },
    {
      "speaker": "S1",
      "tier": "T1",
      "start_time_ms": 73227,
      "end_time_ms": 74042,
      "num_slots": 1,
      "text": "ka wik u taja",
      "dependents": [
        {
          "tier": "T2",
          "values": [
            {
              "start_slot": 0,
              "end_slot": 1,
              "value": "la wilik u tajal"
            }
          ]
        },
        {
          "tier": "T3",
          "values": [
            {
              "start_slot": 0,
              "end_slot": 1,
              "value": "ves que que se cuesa "
            }
          ]
        }
      ]
    },
    {
      "speaker": "S1",
      "tier": "T1",
      "start_time_ms": 74480,
      "end_time_ms": 75805,
      "num_slots": 1,
      "text": "e.. up'ée oora kun...",
      "dependents": [
        {
          "tier": "T2",
          "values": [
            {
              "start_slot": 0,
              "end_slot": 1,
              "value": "e... jump'éel oora kun..."
            }
          ]
        },
        {
          "tier": "T3",
          "values": [
            {
              "start_slot": 0,
              "end_slot": 1,
              "value": "una hora se va a..."
            }
          ]
        }
      ]
    },
    {
      "speaker": "S1",
      "tier": "T1",
      "start_time_ms": 76170,
      "end_time_ms": 77545,
      "num_slots": 1,
      "text": "chéen tajke jkaax túun beyo'",
      "dependents": [
        {
          "tier": "T2",
          "values": [
            {
              "start_slot": 0,
              "end_slot": 1,
              "value": "chéen tajak le jkaax túun beyo'"
            }
          ]
        },
        {
          "tier": "T3",
          "values": [
            {
              "start_slot": 0,
              "end_slot": 1,
              "value": "cuando se cuesa el pollo entonces"
            }
          ]
        }
      ]
    },
    {
      "speaker": "S1",
      "tier": "T1",
      "start_time_ms": 77570,
      "end_time_ms": 78215,
      "num_slots": 1,
      "text": "ka jo'osik,",
      "dependents": [
        {
          "tier": "T2",
          "values": [
            {
              "start_slot": 0,
              "end_slot": 1,
              "value": "ka jo'osik,"
            }
          ]
        },
        {
          "tier": "T3",
          "values": [
            {
              "start_slot": 0,
              "end_slot": 1,
              "value": "lo sacas,"
            }
          ]
        }
      ]
    },
    {
      "speaker": "S1",
      "tier": "T1",
      "start_time_ms": 79385,
      "end_time_ms": 80475,
      "num_slots": 1,
      "text": "ka jo'osik beyo'",
      "dependents": [
        {
          "tier": "T2",
          "values": [
            {
              "start_slot": 0,
              "end_slot": 1,
              "value": "ka jo'osik beyo'"
            }
          ]
        },
        {
          "tier": "T3",
          "values": [
            {
              "start_slot": 0,
              "end_slot": 1,
              "value": "lo sacas así"
            }
          ]
        }
      ]
    },
    {
      "speaker": "S1",
      "tier": "T1",
      "start_time_ms": 80855,
      "end_time_ms": 82355,
      "num_slots": 1,
      "text": "ka p'ayke seboyaa",
      "dependents": [
        {
          "tier": "T2",
          "values": [
            {
              "start_slot": 0,
              "end_slot": 1,
              "value": "ka p'ayik le seboyaa"
            }
          ]
        },
        {
          "tier": "T3",
          "values": [
            {
              "start_slot": 0,
              "end_slot": 1,
              "value": "picas la cebolla"
            }
          ]
        }
      ]
    },
    {
      "speaker": "S1",
      "tier": "T1",
      "start_time_ms": 83300,
      "end_time_ms": 83685,
      "num_slots": 1,
      "text": "p'aak",
      "dependents": [
        {
          "tier": "T2",
          "values": [
            {
              "start_slot": 0,
              "end_slot": 1,
              "value": "p'aak"
            }
          ]
        },
        {
          "tier": "T3",
          "values": [
            {
              "start_slot": 0,
              "end_slot": 1,
              "value": "tomate"
            }
          ]
        }
      ]
    },
    {
      "speaker": "S1",
      "tier": "T1",
      "start_time_ms": 85185,
      "end_time_ms": 86255,
      "num_slots": 1,
      "text": "yéetele morono',",
      "dependents": [
        {
          "tier": "T2",
          "values": [
            {
              "start_slot": 0,
              "end_slot": 1,
              "value": "yéetel le morono',"
            }
          ]
        },
        {
          "tier": "T3",
          "values": [
            {
              "start_slot": 0,
              "end_slot": 1,
              "value": "y el morrón,"
            }
          ]
        }
      ]
    },
    {
      "speaker": "S1",
      "tier": "T1",
      "start_time_ms": 86670,
      "end_time_ms": 88660,
      "num_slots": 1,
      "text": "ka xotke e... e liimao'.",
      "dependents": [
        {
          "tier": "T2",
          "values": [
            {
              "start_slot": 0,
              "end_slot": 1,
              "value": "ka xotik le liimao'."
            }
          ]
        },
        {
          "tier": "T3",
          "values": [
            {
              "start_slot": 0,
              "end_slot": 1,
              "value": "cortas la lima."
            }
          ]
        }
      ]
    },
    {
      "speaker": "S1",
      "tier": "T1",
      "start_time_ms": 90095,
      "end_time_ms": 90390,
      "num_slots": 1,
      "text": "Chéen ts'o'ojke'",
      "dependents": [
        {
          "tier": "T2",
          "values": [
            {
              "start_slot": 0,
              "end_slot": 1,
              "value": "chéen ts'o'ojke'"
            }
          ]
        },
        {
          "tier": "T3",
          "values": [
            {
              "start_slot": 0,
              "end_slot": 1,
              "value": "Después"
            }
          ]
        }
      ]
    },
    {
      "speaker": "S1",
      "tier": "T1",
      "start_time_ms": 90415,
      "end_time_ms": 91790,
      "num_slots": 1,
      "text": "ka láalik bey ichilo'",
      "dependents": [
        {
          "tier": "T2",
          "values": [
            {
              "start_slot": 0,
              "end_slot": 1,
              "value": "ka láalik bey ichilo'"
            }
          ]
        },
        {
          "tier": "T3",
          "values": [
            {
              "start_slot": 0,
              "end_slot": 1,
              "value": "se lo echas adentro así"
            }
          ]
        }
      ]
    },
    {
      "speaker": "S1",
      "tier": "T1",
      "start_time_ms": 91870,
      "end_time_ms": 92885,
      "num_slots": 1,
      "text": "ka ts'áaik kóonsomej",
      "dependents": [
        {
          "tier": "T2",
          "values": [
            {
              "start_slot": 0,
              "end_slot": 1,
              "value": "ka ts'áaik kóonsomej"
            }
          ]
        },
        {
          "tier": "T3",
          "values": [
            {
              "start_slot": 0,
              "end_slot": 1,
              "value": "le pones consome"
            }
          ]
        }
      ]
    },
    {
      "speaker": "S1",
      "tier": "T1",
      "start_time_ms": 92962,
      "end_time_ms": 94197,
      "num_slots": 1,
      "text": "te iche kaaldooo',",
      "dependents": [
        {
          "tier": "T2",
          "values": [
            {
              "start_slot": 0,
              "end_slot": 1,
              "value": "te' ichil le kaaldoo',"
            }
          ]
        },
        {
          "tier": "T3",
          "values": [
            {
              "start_slot": 0,
              "end_slot": 1,
              "value": "dentro del caldo,"
            }
          ]
        }
      ]
    },
    {
      "speaker": "S1",
      "tier": "T1",
      "start_time_ms": 95287,
      "end_time_ms": 96937,
      "num_slots": 1,
      "text": "ka láaj láalke e... e",
      "dependents": [
        {
          "tier": "T2",
          "values": [
            {
              "start_slot": 0,
              "end_slot": 1,
              "value": "ka láaj láalke e... e"
            }
          ]
        },
        {
          "tier": "T3",
          "values": [
            {
              "start_slot": 0,
              "end_slot": 1,
              "value": "echas todas las... las "
            }
          ]
        }
      ]
    },
    {
      "speaker": "S1",
      "tier": "T1",
      "start_time_ms": 97345,
      "end_time_ms": 98500,
      "num_slots": 1,
      "text": "e ba'alob ku bisko'",
      "dependents": [
        {
          "tier": "T2",
          "values": [
            {
              "start_slot": 0,
              "end_slot": 1,
              "value": "le ba'alo'ob ku bisiko'"
            }
          ]
        },
        {
          "tier": "T3",
          "values": [
            {
              "start_slot": 0,
              "end_slot": 1,
              "value": "las cosas que lleva"
            }
          ]
        }
      ]
    },
    {
      "speaker": "S1",
      "tier": "T1",
      "start_time_ms": 98555,
      "end_time_ms": 98990,
      "num_slots": 1,
      "text": "yéetel le,",
      "dependents": [
        {
          "tier": "T2",
          "values": [
            {
              "start_slot": 0,
              "end_slot": 1,
              "value": "yéetel le,"
            }
          ]
        },
        {
          "tier": "T3",
          "values": [
            {
              "start_slot": 0,
              "end_slot": 1,
              "value": "con el,"
            }
          ]
        }
      ]
    },
    {
      "speaker": "S1",
      "tier": "T1",
      "start_time_ms": 99625,
      "end_time_ms": 101090,
      "num_slots": 1,
      "text": "beye... e morono'",
      "dependents": [
        {
          "tier": "T2",
          "values": [
            {
              "start_slot": 0,
              "end_slot": 1,
              "value": "bey le morono'"
            }
          ]
        },
        {
          "tier": "T3",
          "values": [
            {
              "start_slot": 0,
              "end_slot": 1,
              "value": "como el morrón"
            }
          ]
        }
      ]
    },
    {
      "speaker": "S1",
      "tier": "T1",
      "start_time_ms": 101300,
      "end_time_ms": 102170,
      "num_slots": 1,
      "text": "estene e...",
      "dependents": [
        {
          "tier": "T2",
          "values": [
            {
              "start_slot": 0,
              "end_slot": 1,
              "value": "estene e..."
            }
          ]
        },
        {
          "tier": "T3",
          "values": [
            {
              "start_slot": 0,
              "end_slot": 1,
              "value": "esten la"
            }
          ]
        }
      ]
    },
    {
      "speaker": "S1",
      "tier": "T1",
      "start_time_ms": 103670,
      "end_time_ms": 105185,
      "num_slots": 1,
      "text": "seboya yéetel le p'aako'.",
      "dependents": [
        {
          "tier": "T2",
          "values": [
            {
              "start_slot": 0,
              "end_slot": 1,
              "value": "seboya yéetel le p'aako'."
            }
          ]
        },
        {
          "tier": "T3",
          "values": [
            {
              "start_slot": 0,
              "end_slot": 1,
              "value": "cebolla y el tomate."
            }
          ]
        }
      ]
    },
    {
      "speaker": "S1",
      "tier": "T1",
      "start_time_ms": 106305,
      "end_time_ms": 106990,
      "num_slots": 1,
      "text": "Chéen ts'o'okok túune'",
      "dependents": [
        {
          "tier": "T2",
          "values": [
            {
              "start_slot": 0,
              "end_slot": 1,
              "value": "chéen ts'o'okok túune'"
            }
          ]
        },
        {
          "tier": "T3",
          "values": [
            {
              "start_slot": 0,
              "end_slot": 1,
              "value": "Después entonces"
            }
          ]
        }
      ]
    },
    {
      "speaker": "S1",
      "tier": "T1",
      "start_time_ms": 107055,
      "end_time_ms": 108300,
      "num_slots": 1,
      "text": "ka p'ayke e... e... soopa..",
      "dependents": [
        {
          "tier": "T2",
          "values": [
            {
              "start_slot": 0,
              "end_slot": 1,
              "value": "ka p'ayik le... le soop.."
            }
          ]
        },
        {
          "tier": "T3",
          "values": [
            {
              "start_slot": 0,
              "end_slot": 1,
              "value": "picas la... la sop[a]"
            }
          ]
        }
      ]
    },
    {
      "speaker": "S1",
      "tier": "T1",
      "start_time_ms": 108442,
      "end_time_ms": 109692,
      "num_slots": 1,
      "text": "estene le liimao'",
      "dependents": [
        {
          "tier": "T2",
          "values": [
            {
              "start_slot": 0,
              "end_slot": 1,
              "value": "estene le liimao'"
            }
          ]
        },
        {
          "tier": "T3",
          "values": [
            {
              "start_slot": 0,
              "end_slot": 1,
              "value": "esten la lima"
            }
          ]
        }
      ]
    },
    {
      "speaker": "S1",
      "tier": "T1",
      "start_time_ms": 110305,
      "end_time_ms": 111055,
      "num_slots": 1,
      "text": "ka yets'ik",
      "dependents": [
        {
          "tier": "T2",
          "values": [
            {
              "start_slot": 0,
              "end_slot": 1,
              "value": "ka yets'ik"
            }
          ]
        },
        {
          "tier": "T3",
          "values": [
            {
              "start_slot": 0,
              "end_slot": 1,
              "value": "lo exprimes"
            }
          ]
        }
      ]
    },
    {
      "speaker": "S1",
      "tier": "T1",
      "start_time_ms": 111680,
      "end_time_ms": 112765,
      "num_slots": 1,
      "text": "chéen ts'o'ojka yets'ke'",
      "dependents": [
        {
          "tier": "T2",
          "values": [
            {
              "start_slot": 0,
              "end_slot": 1,
              "value": "chéen ts'o'okok a yets'ike'"
            }
          ]
        },
        {
          "tier": "T3",
          "values": [
            {
              "start_slot": 0,
              "end_slot": 1,
              "value": "cuando termines de exprimirlo"
            }
          ]
        }
      ]
    },
    {
      "speaker": "S1",
      "tier": "T1",
      "start_time_ms": 113645,
      "end_time_ms": 113995,
      "num_slots": 1,
      "text": "ka",
      "dependents": [
        {
          "tier": "T2",
          "values": [
            {
              "start_slot": 0,
              "end_slot": 1,
              "value": "ka"
            }
          ]
        },
        {
          "tier": "T3",
          "values": [
            {
              "start_slot": 0,
              "end_slot": 1,
              "value": "lo"
            }
          ]
        }
      ]
    },
    {
      "speaker": "S1",
      "tier": "T1",
      "start_time_ms": 114045,
      "end_time_ms": 114635,
      "num_slots": 1,
      "text": "estenela",
      "dependents": [
        {
          "tier": "T2",
          "values": [
            {
              "start_slot": 0,
              "end_slot": 1,
              "value": "estenela"
            }
          ]
        },
        {
          "tier": "T3",
          "values": [
            {
              "start_slot": 0,
              "end_slot": 1,
              "value": "esten"
            }
          ]
        }
      ]
    },
    {
      "speaker": "S1",
      "tier": "T1",
      "start_time_ms": 114690,
      "end_time_ms": 115995,
      "num_slots": 1,
      "text": "ts'áaik te' ichile kaaldooo',",
      "dependents": [
        {
          "tier": "T2",
          "values": [
            {
              "start_slot": 0,
              "end_slot": 1,
              "value": "ts'áaik te' ichil le kaaldooo',"
            }
          ]
        },
        {
          "tier": "T3",
          "values": [
            {
              "start_slot": 0,
              "end_slot": 1,
              "value": "pones dentro del caldo,"
            }
          ]
        }
      ]
    },
    {
      "speaker": "S1",
      "tier": "T1",
      "start_time_ms": 116107,
      "end_time_ms": 117397,
      "num_slots": 1,
      "text": "ka kalkulaartik bey",
      "dependents": [
        {
          "tier": "T2",
          "values": [
            {
              "start_slot": 0,
              "end_slot": 1,
              "value": "ka kalkulaartik bey"
            }
          ]
        },
        {
          "tier": "T3",
          "values": [
            {
              "start_slot": 0,
              "end_slot": 1,
              "value": "calculas que "
            }
          ]
        }
      ]
    },
    {
      "speaker": "S1",
      "tier": "T1",
      "start_time_ms": 118070,
      "end_time_ms": 119640,
      "num_slots": 1,
      "text": "chan k'as paj le kaaldooo'",
      "dependents": [
        {
          "tier": "T2",
          "values": [
            {
              "start_slot": 0,
              "end_slot": 1,
              "value": "chan k'as paj le kaaldooo'"
            }
          ]
        },
        {
          "tier": "T3",
          "values": [
            {
              "start_slot": 0,
              "end_slot": 1,
              "value": "este medio agrio el caldo"
            }
          ]
        }
      ]
    },
    {
      "speaker": "S1",
      "tier": "T1",
      "start_time_ms": 120320,
      "end_time_ms": 121125,
      "num_slots": 1,
      "text": "chéen ts'o'ojke' ka",
      "dependents": [
        {
          "tier": "T2",
          "values": [
            {
              "start_slot": 0,
              "end_slot": 1,
              "value": "chéen ts'o'okoke'"
            }
          ]
        },
        {
          "tier": "T3",
          "values": [
            {
              "start_slot": 0,
              "end_slot": 1,
              "value": "después le"
            }
          ]
        }
      ]
    },
    {
      "speaker": "S1",
      "tier": "T1",
      "start_time_ms": 121795,
      "end_time_ms": 122715,
      "num_slots": 1,
      "text": "ts'áak tak",
      "dependents": [
        {
          "tier": "T2",
          "values": [
            {
              "start_slot": 0,
              "end_slot": 1,
              "value": "ts'áaik tak"
            }
          ]
        },
        {
          "tier": "T3",
          "values": [
            {
              "start_slot": 0,
              "end_slot": 1,
              "value": "pones hasta"
            }
          ]
        }
      ]
    },
    {
      "speaker": "S1",
      "tier": "T1",
      "start_time_ms": 123140,
      "end_time_ms": 124845,
      "num_slots": 1,
      "text": "siinko up'éelel u xóot'ol ",
      "dependents": [
        {
          "tier": "T2",
          "values": [
            {
              "start_slot": 0,
              "end_slot": 1,
              "value": "siinko jump'éelel u xóot'ol "
            }
          ]
        },
        {
          "tier": "T3",
          "values": [
            {
              "start_slot": 0,
              "end_slot": 1,
              "value": "cinco pedazos "
            }
          ]
        }
      ]
    },
    {
      "speaker": "S1",
      "tier": "T1",
      "start_time_ms": 124852,
      "end_time_ms": 126057,
      "num_slots": 1,
      "text": "le mejen liima ichilo'.",
      "dependents": [
        {
          "tier": "T2",
          "values": [
            {
              "start_slot": 0,
              "end_slot": 1,
              "value": "le mejen liima ichilo'."
            }
          ]
        },
        {
          "tier": "T3",
          "values": [
            {
              "start_slot": 0,
              "end_slot": 1,
              "value": "de las limas adentro."
            }
          ]
        }
      ]
    },
    {
      "speaker": "S1",
      "tier": "T1",
      "start_time_ms": 127680,
      "end_time_ms": 128440,
      "num_slots": 1,
      "text": "Chéen ts'o'ojke'",
      "dependents": [
        {
          "tier": "T2",
          "values": [
            {
              "start_slot": 0,
              "end_slot": 1,
              "value": "chéen ts'o'okoke'"
            }
          ]
        },
        {
          "tier": "T3",
          "values": [
            {
              "start_slot": 0,
              "end_slot": 1,
              "value": "Después"
            }
          ]
        }
      ]
    },
    {
      "speaker": "S1",
      "tier": "T1",
      "start_time_ms": 128450,
      "end_time_ms": 131010,
      "num_slots": 1,
      "text": "ka ts'áaka... tíitke kóonsome ichilo'",
      "dependents": [
        {
          "tier": "T2",
          "values": [
            {
              "start_slot": 0,
              "end_slot": 1,
              "value": "ka ts'áaik a... tíitik le kóomsomej ichilo'"
            }
          ]
        },
        {
          "tier": "T3",
          "values": [
            {
              "start_slot": 0,
              "end_slot": 1,
              "value": "le pones... echas el consome adentro"
            }
          ]
        }
      ]
    },
    {
      "speaker": "S1",
      "tier": "T1",
      "start_time_ms": 132550,
      "end_time_ms": 132885,
      "num_slots": 1,
      "text": "ka",
      "dependents": [
        {
          "tier": "T2",
          "values": [
            {
              "start_slot": 0,
              "end_slot": 1,
              "value": "ka"
            }
          ]
        },
        {
          "tier": "T3",
          "values": [
            {
              "start_slot": 0,
              "end_slot": 1,
              "value": "le"
            }
          ]
        }
      ]
    },
    {
      "speaker": "S1",
      "tier": "T1",
      "start_time_ms": 132967,
      "end_time_ms": 133617,
      "num_slots": 1,
      "text": "estenala",
      "dependents": [
        {
          "tier": "T2",
          "values": [
            {
              "start_slot": 0,
              "end_slot": 1,
              "value": "estenela"
            }
          ]
        },
        {
          "tier": "T3",
          "values": [
            {
              "start_slot": 0,
              "end_slot": 1,
              "value": "esten"
            }
          ]
        }
      ]
    },
    {
      "speaker": "S1",
      "tier": "T1",
      "start_time_ms": 133662,
      "end_time_ms": 135162,
      "num_slots": 1,
      "text": "ts'áak up'íit xa'ak'i'",
      "dependents": [
        {
          "tier": "T2",
          "values": [
            {
              "start_slot": 0,
              "end_slot": 1,
              "value": "ts'áaik jump'íit xa'ak'i'"
            }
          ]
        },
        {
          "tier": "T3",
          "values": [
            {
              "start_slot": 0,
              "end_slot": 1,
              "value": "pones un poco de recado"
            }
          ]
        }
      ]
    },
    {
      "speaker": "S1",
      "tier": "T1",
      "start_time_ms": 136095,
      "end_time_ms": 136945,
      "num_slots": 1,
      "text": "perone xa'ak'o'",
      "dependents": [
        {
          "tier": "T2",
          "values": [
            {
              "start_slot": 0,
              "end_slot": 1,
              "value": "pero le xa'ak'o'"
            }
          ]
        },
        {
          "tier": "T3",
          "values": [
            {
              "start_slot": 0,
              "end_slot": 1,
              "value": "pero el recado"
            }
          ]
        }
      ]
    },
    {
      "speaker": "S1",
      "tier": "T1",
      "start_time_ms": 136950,
      "end_time_ms": 137690,
      "num_slots": 1,
      "text": "ma' ya'ab ku biski'",
      "dependents": [
        {
          "tier": "T2",
          "values": [
            {
              "start_slot": 0,
              "end_slot": 1,
              "value": "ma' ya'ab ku bisiki'"
            }
          ]
        },
        {
          "tier": "T3",
          "values": [
            {
              "start_slot": 0,
              "end_slot": 1,
              "value": "no mucho lleva"
            }
          ]
        }
      ]
    },
    {
      "speaker": "S1",
      "tier": "T1",
      "start_time_ms": 138155,
      "end_time_ms": 138820,
      "num_slots": 1,
      "text": "chenu p'íit",
      "dependents": [
        {
          "tier": "T2",
          "values": [
            {
              "start_slot": 0,
              "end_slot": 1,
              "value": "chéen jump'íit"
            }
          ]
        },
        {
          "tier": "T3",
          "values": [
            {
              "start_slot": 0,
              "end_slot": 1,
              "value": "solo un poco"
            }
          ]
        }
      ]
    },
    {
      "speaker": "S1",
      "tier": "T1",
      "start_time_ms": 139790,
      "end_time_ms": 141590,
      "num_slots": 1,
      "text": "chéen ti'al ku ts'áa guusto.",
      "dependents": [
        {
          "tier": "T2",
          "values": [
            {
              "start_slot": 0,
              "end_slot": 1,
              "value": "chéen ti'al ka u ts'áa guusto."
            }
          ]
        },
        {
          "tier": "T3",
          "values": [
            {
              "start_slot": 0,
              "end_slot": 1,
              "value": "solo para que le de sabor."
            }
          ]
        }
      ]
    },
    {
      "speaker": "S1",
      "tier": "T1",
      "start_time_ms": 143120,
      "end_time_ms": 144650,
      "num_slots": 1,
      "text": "E... ku ts'áaba túune",
      "dependents": [
        {
          "tier": "T2",
          "values": [
            {
              "start_slot": 0,
              "end_slot": 1,
              "value": "ku tsa'áabal túun le"
            }
          ]
        },
        {
          "tier": "T3",
          "values": [
            {
              "start_slot": 0,
              "end_slot": 1,
              "value": "entonces le ponen la"
            }
          ]
        }
      ]
    },
    {
      "speaker": "S1",
      "tier": "T1",
      "start_time_ms": 144805,
      "end_time_ms": 147150,
      "num_slots": 1,
      "text": "oojaile e... lawrel ichilo'.",
      "dependents": [
        {
          "tier": "T2",
          "values": [
            {
              "start_slot": 0,
              "end_slot": 1,
              "value": "oojaile e... lawrel ichilo'."
            }
          ]
        },
        {
          "tier": "T3",
          "values": [
            {
              "start_slot": 0,
              "end_slot": 1,
              "value": "hoja del laurel adentro."
            }
          ]
        }
      ]
    },
    {
      "speaker": "S1",
      "tier": "T1",
      "start_time_ms": 148615,
      "end_time_ms": 150065,
      "num_slots": 1,
      "text": "E... chéen ts'o'okok túun beyo'",
      "dependents": [
        {
          "tier": "T2",
          "values": [
            {
              "start_slot": 0,
              "end_slot": 1,
              "value": "E... chéen ts'o'okok túun beyo'"
            }
          ]
        },
        {
          "tier": "T3",
          "values": [
            {
              "start_slot": 0,
              "end_slot": 1,
              "value": "cuando termine así entonces "
            }
          ]
        }
      ]
    },
    {
      "speaker": "S1",
      "tier": "T1",
      "start_time_ms": 150855,
      "end_time_ms": 151435,
      "num_slots": 1,
      "text": "e... chéen",
      "dependents": [
        {
          "tier": "T2",
          "values": [
            {
              "start_slot": 0,
              "end_slot": 1,
              "value": "e... chéen "
            }
          ]
        },
        {
          "tier": "T3",
          "values": [
            {
              "start_slot": 0,
              "end_slot": 1,
              "value": "e... cuando"
            }
          ]
        }
      ]
    },
    {
      "speaker": "S1",
      "tier": "T1",
      "start_time_ms": 152210,
      "end_time_ms": 153525,
      "num_slots": 1,
      "text": "chéen láaj tajak túun beyo'",
      "dependents": [
        {
          "tier": "T2",
          "values": [
            {
              "start_slot": 0,
              "end_slot": 1,
              "value": "chéen láaj tajak túun beyo"
            }
          ]
        },
        {
          "tier": "T3",
          "values": [
            {
              "start_slot": 0,
              "end_slot": 1,
              "value": "cuando se cuesa todo entonces"
            }
          ]
        }
      ]
    },
    {
      "speaker": "S1",
      "tier": "T1",
      "start_time_ms": 153582,
      "end_time_ms": 154292,
      "num_slots": 1,
      "text": "chéen looknake",
      "dependents": [
        {
          "tier": "T2",
          "values": [
            {
              "start_slot": 0,
              "end_slot": 1,
              "value": "chéen looknak le"
            }
          ]
        },
        {
          "tier": "T3",
          "values": [
            {
              "start_slot": 0,
              "end_slot": 1,
              "value": "cuando hierva el"
            }
          ]
        }
      ]
    },
    {
      "speaker": "S1",
      "tier": "T1",
      "start_time_ms": 154325,
      "end_time_ms": 155225,
      "num_slots": 1,
      "text": "e... e... e...",
      "dependents": [
        {
          "tier": "T2",
          "values": [
            {
              "start_slot": 0,
              "end_slot": 1,
              "value": "e... e... e...."
            }
          ]
        },
        {
          "tier": "T3",
          "values": [
            {
              "start_slot": 0,
              "end_slot": 1,
              "value": "el... el... el"
            }
          ]
        }
      ]
    },
    {
      "speaker": "S1",
      "tier": "T1",
      "start_time_ms": 155820,
      "end_time_ms": 157900,
      "num_slots": 1,
      "text": "kaaldo bey yéetele e... e... e...",
      "dependents": [
        {
          "tier": "T2",
          "values": [
            {
              "start_slot": 0,
              "end_slot": 1,
              "value": "kaaldo bey yéetel le e... e... e..."
            }
          ]
        },
        {
          "tier": "T3",
          "values": [
            {
              "start_slot": 0,
              "end_slot": 1,
              "value": "caldo así con la la... la... la..."
            }
          ]
        }
      ]
    },
    {
      "speaker": "S1",
      "tier": "T1",
      "start_time_ms": 158160,
      "end_time_ms": 159160,
      "num_slots": 1,
      "text": "e seboya,",
      "dependents": [
        {
          "tier": "T2",
          "values": [
            {
              "start_slot": 0,
              "end_slot": 1,
              "value": "le seboya,"
            }
          ]
        },
        {
          "tier": "T3",
          "values": [
            {
              "start_slot": 0,
              "end_slot": 1,
              "value": "la cebolla,"
            }
          ]
        }
      ]
    },
    {
      "speaker": "S1",
      "tier": "T1",
      "start_time_ms": 159170,
      "end_time_ms": 160100,
      "num_slots": 1,
      "text": "e p'aako'",
      "dependents": [
        {
          "tier": "T2",
          "values": [
            {
              "start_slot": 0,
              "end_slot": 1,
              "value": "le p'aako'"
            }
          ]
        },
        {
          "tier": "T3",
          "values": [
            {
              "start_slot": 0,
              "end_slot": 1,
              "value": "el tomate"
            }
          ]
        }
      ]
    },
    {
      "speaker": "S1",
      "tier": "T1",
      "start_time_ms": 162380,
      "end_time_ms": 163255,
      "num_slots": 1,
      "text": "ku chúuya'a túun.",
      "dependents": [
        {
          "tier": "T2",
          "values": [
            {
              "start_slot": 0,
              "end_slot": 1,
              "value": "ku ch'úuya'al túun."
            }
          ]
        },
        {
          "tier": "T3",
          "values": [
            {
              "start_slot": 0,
              "end_slot": 1,
              "value": "se alza entonces."
            }
          ]
        }
      ]
    },
    {
      "speaker": "S1",
      "tier": "T1",
      "start_time_ms": 163402,
      "end_time_ms": 164692,
      "num_slots": 1,
      "text": "E chéen ch'úuya'ak túuno'",
      "dependents": [
        {
          "tier": "T2",
          "values": [
            {
              "start_slot": 0,
              "end_slot": 1,
              "value": "Le chéen ch'úuya'ak túuno'"
            }
          ]
        },
        {
          "tier": "T3",
          "values": [
            {
              "start_slot": 0,
              "end_slot": 1,
              "value": "Cuando se alce entonces"
            }
          ]
        }
      ]
    },
    {
      "speaker": "S1",
      "tier": "T1",
      "start_time_ms": 165707,
      "end_time_ms": 166702,
      "num_slots": 1,
      "text": "ku pa'aya waaj",
      "dependents": [
        {
          "tier": "T2",
          "values": [
            {
              "start_slot": 0,
              "end_slot": 1,
              "value": "ku p'a'ayal waaj"
            }
          ]
        },
        {
          "tier": "T3",
          "values": [
            {
              "start_slot": 0,
              "end_slot": 1,
              "value": "se corta tortilla"
            }
          ]
        }
      ]
    },
    {
      "speaker": "S1",
      "tier": "T1",
      "start_time_ms": 167620,
      "end_time_ms": 169735,
      "num_slots": 1,
      "text": "de... de... de mejen chowaktak",
      "dependents": [
        {
          "tier": "T2",
          "values": [
            {
              "start_slot": 0,
              "end_slot": 1,
              "value": "de... de... de mejen chowaktak"
            }
          ]
        },
        {
          "tier": "T3",
          "values": [
            {
              "start_slot": 0,
              "end_slot": 1,
              "value": "de... de... de larguitos"
            }
          ]
        }
      ]
    },
    {
      "speaker": "S1",
      "tier": "T1",
      "start_time_ms": 170240,
      "end_time_ms": 171735,
      "num_slots": 1,
      "text": "chéen ts'o'ojke' ku tsa'ajal",
      "dependents": [
        {
          "tier": "T2",
          "values": [
            {
              "start_slot": 0,
              "end_slot": 1,
              "value": "chéen ts'o'ojke ku tsa'ajal"
            }
          ]
        },
        {
          "tier": "T3",
          "values": [
            {
              "start_slot": 0,
              "end_slot": 1,
              "value": "después se fríe"
            }
          ]
        }
      ]
    },
    {
      "speaker": "S1",
      "tier": "T1",
      "start_time_ms": 172315,
      "end_time_ms": 172790,
      "num_slots": 1,
      "text": "chéen ts'o'ojke'",
      "dependents": [
        {
          "tier": "T2",
          "values": [
            {
              "start_slot": 0,
              "end_slot": 1,
              "value": "chéen ts'o'ojke'"
            }
          ]
        },
        {
          "tier": "T3",
          "values": [
            {
              "start_slot": 0,
              "end_slot": 1,
              "value": "después"
            }
          ]
        }
      ]
    },
    {
      "speaker": "S1",
      "tier": "T1",
      "start_time_ms": 172852,
      "end_time_ms": 174257,
      "num_slots": 1,
      "text": "ku tsi'ikta'al le jkaaxo'",
      "dependents": [
        {
          "tier": "T2",
          "values": [
            {
              "start_slot": 0,
              "end_slot": 1,
              "value": "ku tsi'ikta'al le jkaaxo'"
            }
          ]
        },
        {
          "tier": "T3",
          "values": [
            {
              "start_slot": 0,
              "end_slot": 1,
              "value": "se desmenuza el pollo "
            }
          ]
        }
      ]
    },
    {
      "speaker": "S1",
      "tier": "T1",
      "start_time_ms": 175440,
      "end_time_ms": 177160,
      "num_slots": 1,
      "text": "esten... ti'aj ts'áabi te'",
      "dependents": [
        {
          "tier": "T2",
          "values": [
            {
              "start_slot": 0,
              "end_slot": 1,
              "value": "esten... ti'al ts'áabi te'"
            }
          ]
        },
        {
          "tier": "T3",
          "values": [
            {
              "start_slot": 0,
              "end_slot": 1,
              "value": "esten... para que se ponga en "
            }
          ]
        }
      ]
    },
    {
      "speaker": "S1",
      "tier": "T1",
      "start_time_ms": 177870,
      "end_time_ms": 179800,
      "num_slots": 1,
      "text": "ti'a ts'áabi te' estene le e...",
      "dependents": [
        {
          "tier": "T2",
          "values": [
            {
              "start_slot": 0,
              "end_slot": 1,
              "value": "ti'al ts'áabi te' estene le e..."
            }
          ]
        },
        {
          "tier": "T3",
          "values": [
            {
              "start_slot": 0,
              "end_slot": 1,
              "value": "para que se ponga en el esten"
            }
          ]
        }
      ]
    },
    {
      "speaker": "S1",
      "tier": "T1",
      "start_time_ms": 180880,
      "end_time_ms": 182310,
      "num_slots": 1,
      "text": "ichile kaldooo'.",
      "dependents": [
        {
          "tier": "T2",
          "values": [
            {
              "start_slot": 0,
              "end_slot": 1,
              "value": "ichil le kaldooo'."
            }
          ]
        },
        {
          "tier": "T3",
          "values": [
            {
              "start_slot": 0,
              "end_slot": 1,
              "value": "dentro del caldo."
            }
          ]
        }
      ]
    },
    {
      "speaker": "S1",
      "tier": "T1",
      "start_time_ms": 183305,
      "end_time_ms": 185415,
      "num_slots": 1,
      "text": "Chéen ts'o'okok túun beyo'",
      "dependents": [
        {
          "tier": "T2",
          "values": [
            {
              "start_slot": 0,
              "end_slot": 1,
              "value": "chéen ts'o'okok túun beyo'"
            }
          ]
        },
        {
          "tier": "T3",
          "values": [
            {
              "start_slot": 0,
              "end_slot": 1,
              "value": "cuando termine así entonces"
            }
          ]
        }
      ]
    },
    {
      "speaker": "S1",
      "tier": "T1",
      "start_time_ms": 186400,
      "end_time_ms": 187500,
      "num_slots": 1,
      "text": "ku tsi'ikta'al túun beyo'",
      "dependents": [
        {
          "tier": "T2",
          "values": [
            {
              "start_slot": 0,
              "end_slot": 1,
              "value": "ku tsi'ikta'al túun beyo'"
            }
          ]
        },
        {
          "tier": "T3",
          "values": [
            {
              "start_slot": 0,
              "end_slot": 1,
              "value": "se desmenuza así entonces"
            }
          ]
        }
      ]
    },
    {
      "speaker": "S1",
      "tier": "T1",
      "start_time_ms": 187590,
      "end_time_ms": 188855,
      "num_slots": 1,
      "text": "ku ts'áaba ichile e...",
      "dependents": [
        {
          "tier": "T2",
          "values": [
            {
              "start_slot": 0,
              "end_slot": 1,
              "value": "ku ts'áabal ichil le "
            }
          ]
        },
        {
          "tier": "T3",
          "values": [
            {
              "start_slot": 0,
              "end_slot": 1,
              "value": "se ponde dentro del"
            }
          ]
        }
      ]
    },
    {
      "speaker": "S1",
      "tier": "T1",
      "start_time_ms": 189435,
      "end_time_ms": 192640,
      "num_slots": 1,
      "text": "kaaldo yéetel e... e... e...",
      "dependents": [
        {
          "tier": "T2",
          "values": [
            {
              "start_slot": 0,
              "end_slot": 1,
              "value": "kaaldo yéetel le... le... le..."
            }
          ]
        },
        {
          "tier": "T3",
          "values": [
            {
              "start_slot": 0,
              "end_slot": 1,
              "value": "caldo con la... la... la..."
            }
          ]
        }
      ]
    },
    {
      "speaker": "S1",
      "tier": "T1",
      "start_time_ms": 193390,
      "end_time_ms": 194735,
      "num_slots": 1,
      "text": "estene tostaadao'.",
      "dependents": [
        {
          "tier": "T2",
          "values": [
            {
              "start_slot": 0,
              "end_slot": 1,
              "value": "esten le tostaadao'."
            }
          ]
        },
        {
          "tier": "T3",
          "values": [
            {
              "start_slot": 0,
              "end_slot": 1,
              "value": "esten la tostada."
            }
          ]
        }
      ]
    },
    {
      "speaker": "S1",
      "tier": "T1",
      "start_time_ms": 197030,
      "end_time_ms": 197485,
      "num_slots": 1,
      "text": "Beráae',",
      "dependents": [
        {
          "tier": "T2",
          "values": [
            {
              "start_slot": 0,
              "end_slot": 1,
              "value": "Beráae',"
            }
          ]
        },
        {
          "tier": "T3",
          "values": [
            {
              "start_slot": 0,
              "end_slot": 1,
              "value": "Ahora,"
            }
          ]
        }
      ]
    },
    {
      "speaker": "S1",
      "tier": "T1",
      "start_time_ms": 197785,
      "end_time_ms": 198725,
      "num_slots": 1,
      "text": "chéen ts'o'okok túune",
      "dependents": [
        {
          "tier": "T2",
          "values": [
            {
              "start_slot": 0,
              "end_slot": 1,
              "value": "chéen ts'o'okk túune"
            }
          ]
        },
        {
          "tier": "T3",
          "values": [
            {
              "start_slot": 0,
              "end_slot": 1,
              "value": "cuando termine estonces"
            }
          ]
        }
      ]
    },
    {
      "speaker": "S1",
      "tier": "T1",
      "start_time_ms": 199080,
      "end_time_ms": 201755,
      "num_slots": 1,
      "text": "beráae' ts'o'okin eksplikaartik te'exe e... e...",
      "dependents": [
        {
          "tier": "T2",
          "values": [
            {
              "start_slot": 0,
              "end_slot": 1,
              "value": "beráae' ts'o'ok in eksplikaartik te'ex e... e..."
            }
          ]
        },
        {
          "tier": "T3",
          "values": [
            {
              "start_slot": 0,
              "end_slot": 1,
              "value": "ahora ya les explique el... el..."
            }
          ]
        }
      ]
    },
    {
      "speaker": "S1",
      "tier": "T1",
      "start_time_ms": 202810,
      "end_time_ms": 204335,
      "num_slots": 1,
      "text": "ti' le soopa de liimao'",
      "dependents": [
        {
          "tier": "T2",
          "values": [
            {
              "start_slot": 0,
              "end_slot": 1,
              "value": "ti' le soopa de liimao'"
            }
          ]
        },
        {
          "tier": "T3",
          "values": [
            {
              "start_slot": 0,
              "end_slot": 1,
              "value": "lo de la sopa de lima "
            }
          ]
        }
      ]
    },
    {
      "speaker": "S1",
      "tier": "T1",
      "start_time_ms": 204860,
      "end_time_ms": 206630,
      "num_slots": 1,
      "text": "beráae' nuka'ajen in eksplikaarte'exe",
      "dependents": [
        {
          "tier": "T2",
          "values": [
            {
              "start_slot": 0,
              "end_slot": 1,
              "value": "beráae' nuka'ajen in eksplikaarte'exe"
            }
          ]
        },
        {
          "tier": "T3",
          "values": [
            {
              "start_slot": 0,
              "end_slot": 1,
              "value": "ahora les voy a explicar "
            }
          ]
        }
      ]
    },
    {
      "speaker": "S1",
      "tier": "T1",
      "start_time_ms": 207005,
      "end_time_ms": 208170,
      "num_slots": 1,
      "text": "e peebreo'.",
      "dependents": [
        {
          "tier": "T2",
          "values": [
            {
              "start_slot": 0,
              "end_slot": 1,
              "value": "le peebreo'."
            }
          ]
        },
        {
          "tier": "T3",
          "values": [
            {
              "start_slot": 0,
              "end_slot": 1,
              "value": "el pebre."
            }
          ]
        }
      ]
    },
    {
      "speaker": "S1",
      "tier": "T1",
      "start_time_ms": 209145,
      "end_time_ms": 210080,
      "num_slots": 1,
      "text": "E peebreo'",
      "dependents": [
        {
          "tier": "T2",
          "values": [
            {
              "start_slot": 0,
              "end_slot": 1,
              "value": "Le peebreo'"
            }
          ]
        },
        {
          "tier": "T3",
          "values": [
            {
              "start_slot": 0,
              "end_slot": 1,
              "value": "El pebre"
            }
          ]
        }
      ]
    },
    {
      "speaker": "S1",
      "tier": "T1",
      "start_time_ms": 211595,
      "end_time_ms": 212910,
      "num_slots": 1,
      "text": "yana estena la'a",
      "dependents": [
        {
          "tier": "T2",
          "values": [
            {
              "start_slot": 0,
              "end_slot": 1,
              "value": "yaan a estenela a"
            }
          ]
        },
        {
          "tier": "T3",
          "values": [
            {
              "start_slot": 0,
              "end_slot": 1,
              "value": "vas a esten a"
            }
          ]
        }
      ]
    },
    {
      "speaker": "S1",
      "tier": "T1",
      "start_time_ms": 214970,
      "end_time_ms": 216360,
      "num_slots": 1,
      "text": "yana estena la'a",
      "dependents": [
        {
          "tier": "T2",
          "values": [
            {
              "start_slot": 0,
              "end_slot": 1,
              "value": "yaan a estenela a"
            }
          ]
        },
        {
          "tier": "T3",
          "values": [
            {
              "start_slot": 0,
              "end_slot": 1,
              "value": ""
            }
          ]
        }
      ]
    },
    {
      "speaker": "S1",
      "tier": "T1",
      "start_time_ms": 218585,
      "end_time_ms": 220695,
      "num_slots": 1,
      "text": "láayli' beyo' yana p'o'oke jkaaxo'",
      "dependents": [
        {
          "tier": "T2",
          "values": [
            {
              "start_slot": 0,
              "end_slot": 1,
              "value": "láayli' beyo' yaan a p'o'ik le jkaaxo'"
            }
          ]
        },
        {
          "tier": "T3",
          "values": [
            {
              "start_slot": 0,
              "end_slot": 1,
              "value": "lo mismo vas a lavar el pollo"
            }
          ]
        }
      ]
    },
    {
      "speaker": "S1",
      "tier": "T1",
      "start_time_ms": 220810,
      "end_time_ms": 222605,
      "num_slots": 1,
      "text": "ka laj ts'áaik ichile e... e...",
      "dependents": [
        {
          "tier": "T2",
          "values": [
            {
              "start_slot": 0,
              "end_slot": 1,
              "value": "ka laj ts'áaik ichile e... e..."
            }
          ]
        },
        {
          "tier": "T3",
          "values": [
            {
              "start_slot": 0,
              "end_slot": 1,
              "value": "lo pones todo dentro de... de..."
            }
          ]
        }
      ]
    },
    {
      "speaker": "S1",
      "tier": "T1",
      "start_time_ms": 223840,
      "end_time_ms": 225245,
      "num_slots": 1,
      "text": "e... estene ja'o'",
      "dependents": [
        {
          "tier": "T2",
          "values": [
            {
              "start_slot": 0,
              "end_slot": 1,
              "value": "le estene ja'o'"
            }
          ]
        },
        {
          "tier": "T3",
          "values": [
            {
              "start_slot": 0,
              "end_slot": 1,
              "value": "del agua"
            }
          ]
        }
      ]
    },
    {
      "speaker": "S1",
      "tier": "T1",
      "start_time_ms": 225410,
      "end_time_ms": 226420,
      "num_slots": 1,
      "text": "ka ts'áaik te' k'áak'o'.",
      "dependents": [
        {
          "tier": "T2",
          "values": [
            {
              "start_slot": 0,
              "end_slot": 1,
              "value": "ka ts'áaik te' k'áak'o'."
            }
          ]
        },
        {
          "tier": "T3",
          "values": [
            {
              "start_slot": 0,
              "end_slot": 1,
              "value": "lo pones en la candela."
            }
          ]
        }
      ]
    },
    {
      "speaker": "S1",
      "tier": "T1",
      "start_time_ms": 227815,
      "end_time_ms": 230005,
      "num_slots": 1,
      "text": "chéen ts'o'okok túun beyo', chéen oku look túun beyo'",
      "dependents": [
        {
          "tier": "T2",
          "values": [
            {
              "start_slot": 0,
              "end_slot": 1,
              "value": "chéen ts'o'okok túun beyo' chéen jo'op' u look túun beyo'"
            }
          ]
        },
        {
          "tier": "T3",
          "values": [
            {
              "start_slot": 0,
              "end_slot": 1,
              "value": "cuando termine así esntonces cuando este hirviendo así entonces"
            }
          ]
        }
      ]
    },
    {
      "speaker": "S1",
      "tier": "T1",
      "start_time_ms": 230020,
      "end_time_ms": 232415,
      "num_slots": 1,
      "text": "chéen tajke jkaaxo' ka jo'oske jkaaxo'",
      "dependents": [
        {
          "tier": "T2",
          "values": [
            {
              "start_slot": 0,
              "end_slot": 1,
              "value": "chéen tajke jkaaxo' ka jo'osik le jkaaxo'"
            }
          ]
        },
        {
          "tier": "T3",
          "values": [
            {
              "start_slot": 0,
              "end_slot": 1,
              "value": "cuando se cuesa el pollo, sacas el pollo"
            }
          ]
        }
      ]
    },
    {
      "speaker": "S1",
      "tier": "T1",
      "start_time_ms": 233615,
      "end_time_ms": 234835,
      "num_slots": 1,
      "text": "ka estenala",
      "dependents": [
        {
          "tier": "T2",
          "values": [
            {
              "start_slot": 0,
              "end_slot": 1,
              "value": "ka esten alaj"
            }
          ]
        },
        {
          "tier": "T3",
          "values": [
            {
              "start_slot": 0,
              "end_slot": 1,
              "value": "le esten.."
            }
          ]
        }
      ]
    },
    {
      "speaker": "S1",
      "tier": "T1",
      "start_time_ms": 236220,
      "end_time_ms": 237945,
      "num_slots": 1,
      "text": "ka ts'áake e... e...",
      "dependents": [
        {
          "tier": "T2",
          "values": [
            {
              "start_slot": 0,
              "end_slot": 1,
              "value": "ka ts'áaik le e... e..."
            }
          ]
        },
        {
          "tier": "T3",
          "values": [
            {
              "start_slot": 0,
              "end_slot": 1,
              "value": "le pones la... la... la"
            }
          ]
        }
      ]
    },
    {
      "speaker": "S1",
      "tier": "T1",
      "start_time_ms": 238070,
      "end_time_ms": 239595,
      "num_slots": 1,
      "text": "ka bok'ke áarinao'",
      "dependents": [
        {
          "tier": "T2",
          "values": [
            {
              "start_slot": 0,
              "end_slot": 1,
              "value": "ka bok'ik le áarinao'"
            }
          ]
        },
        {
          "tier": "T3",
          "values": [
            {
              "start_slot": 0,
              "end_slot": 1,
              "value": "diluyes la harina"
            }
          ]
        }
      ]
    },
    {
      "speaker": "S1",
      "tier": "T1",
      "start_time_ms": 239645,
      "end_time_ms": 240505,
      "num_slots": 1,
      "text": "ka ts'áaik ichij",
      "dependents": [
        {
          "tier": "T2",
          "values": [
            {
              "start_slot": 0,
              "end_slot": 1,
              "value": "ka ts'áaik ichij"
            }
          ]
        },
        {
          "tier": "T3",
          "values": [
            {
              "start_slot": 0,
              "end_slot": 1,
              "value": "lo pones adentro"
            }
          ]
        }
      ]
    },
    {
      "speaker": "S1",
      "tier": "T1",
      "start_time_ms": 241120,
      "end_time_ms": 241525,
      "num_slots": 1,
      "text": "chéen ts'o'ojke'",
      "dependents": [
        {
          "tier": "T2",
          "values": [
            {
              "start_slot": 0,
              "end_slot": 1,
              "value": "chéen ts'o'ojke' "
            }
          ]
        },
        {
          "tier": "T3",
          "values": [
            {
              "start_slot": 0,
              "end_slot": 1,
              "value": "después"
            }
          ]
        }
      ]
    },
    {
      "speaker": "S1",
      "tier": "T1",
      "start_time_ms": 241542,
      "end_time_ms": 243097,
      "num_slots": 1,
      "text": "ka ts'áaik pasiitas,",
      "dependents": [
        {
          "tier": "T2",
          "values": [
            {
              "start_slot": 0,
              "end_slot": 1,
              "value": "ka ts'áaik pasiitas,"
            }
          ]
        },
        {
          "tier": "T3",
          "values": [
            {
              "start_slot": 0,
              "end_slot": 1,
              "value": "pones pasitas,"
            }
          ]
        }
      ]
    },
    {
      "speaker": "S1",
      "tier": "T1",
      "start_time_ms": 244005,
      "end_time_ms": 247725,
      "num_slots": 1,
      "text": "aseytuunas, silaantro yéetel chiile duulse.",
      "dependents": [
        {
          "tier": "T2",
          "values": [
            {
              "start_slot": 0,
              "end_slot": 1,
              "value": "aseytuunas, silaantro yéetel chiile duulse."
            }
          ]
        },
        {
          "tier": "T3",
          "values": [
            {
              "start_slot": 0,
              "end_slot": 1,
              "value": "aceitunas, cilantro y chile dulce."
            }
          ]
        }
      ]
    },
    {
      "speaker": "S1",
      "tier": "T1",
      "start_time_ms": 249170,
      "end_time_ms": 250145,
      "num_slots": 1,
      "text": "e... chéen ts'o'okok",
      "dependents": [
        {
          "tier": "T2",
          "values": [
            {
              "start_slot": 0,
              "end_slot": 1,
              "value": "e... chéen ts'o'okok"
            }
          ]
        },
        {
          "tier": "T3",
          "values": [
            {
              "start_slot": 0,
              "end_slot": 1,
              "value": "eh... cuando termine"
            }
          ]
        }
      ]
    },
    {
      "speaker": "S1",
      "tier": "T1",
      "start_time_ms": 250400,
      "end_time_ms": 251425,
      "num_slots": 1,
      "text": "chéen ts'o'okok túun beyo'",
      "dependents": [
        {
          "tier": "T2",
          "values": [
            {
              "start_slot": 0,
              "end_slot": 1,
              "value": "chéen ts'o'okok túun beyo'"
            }
          ]
        },
        {
          "tier": "T3",
          "values": [
            {
              "start_slot": 0,
              "end_slot": 1,
              "value": "cuando termine así entonces"
            }
          ]
        }
      ]
    },
    {
      "speaker": "S1",
      "tier": "T1",
      "start_time_ms": 251455,
      "end_time_ms": 254825,
      "num_slots": 1,
      "text": "chéen tatchajke kaald... estenele e... e... e... k'óol beyo'",
      "dependents": [
        {
          "tier": "T2",
          "values": [
            {
              "start_slot": 0,
              "end_slot": 1,
              "value": "chéen tatchajke kaald... estenele e... e... e... k'óol beyo'"
            }
          ]
        },
        {
          "tier": "T3",
          "values": [
            {
              "start_slot": 0,
              "end_slot": 1,
              "value": "cuando quede espeso el cald[o]... esten el, el... el... el caldo así"
            }
          ]
        }
      ]
    },
    {
      "speaker": "S1",
      "tier": "T1",
      "start_time_ms": 254865,
      "end_time_ms": 255560,
      "num_slots": 1,
      "text": "ka jo'osik",
      "dependents": [
        {
          "tier": "T2",
          "values": [
            {
              "start_slot": 0,
              "end_slot": 1,
              "value": "ka jo'osik"
            }
          ]
        },
        {
          "tier": "T3",
          "values": [
            {
              "start_slot": 0,
              "end_slot": 1,
              "value": "lo sacas"
            }
          ]
        }
      ]
    },
    {
      "speaker": "S1",
      "tier": "T1",
      "start_time_ms": 257085,
      "end_time_ms": 258990,
      "num_slots": 1,
      "text": "ka tsajik tak up'ée...",
      "dependents": [
        {
          "tier": "T2",
          "values": [
            {
              "start_slot": 0,
              "end_slot": 1,
              "value": "ka tsajik tak jump'éel..."
            }
          ]
        },
        {
          "tier": "T3",
          "values": [
            {
              "start_slot": 0,
              "end_slot": 1,
              "value": "fríes hasta un..."
            }
          ]
        }
      ]
    },
    {
      "speaker": "S1",
      "tier": "T1",
      "start_time_ms": 259510,
      "end_time_ms": 260665,
      "num_slots": 1,
      "text": "kiilo p'aak",
      "dependents": [
        {
          "tier": "T2",
          "values": [
            {
              "start_slot": 0,
              "end_slot": 1,
              "value": "kiilo p'aak"
            }
          ]
        },
        {
          "tier": "T3",
          "values": [
            {
              "start_slot": 0,
              "end_slot": 1,
              "value": "kilo de tomate"
            }
          ]
        }
      ]
    },
    {
      "speaker": "S1",
      "tier": "T1",
      "start_time_ms": 261850,
      "end_time_ms": 262780,
      "num_slots": 1,
      "text": "ka likwáartik",
      "dependents": [
        {
          "tier": "T2",
          "values": [
            {
              "start_slot": 0,
              "end_slot": 1,
              "value": "ka likwáartik"
            }
          ]
        },
        {
          "tier": "T3",
          "values": [
            {
              "start_slot": 0,
              "end_slot": 1,
              "value": "lo licúas"
            }
          ]
        }
      ]
    },
    {
      "speaker": "S1",
      "tier": "T1",
      "start_time_ms": 262875,
      "end_time_ms": 263815,
      "num_slots": 1,
      "text": "chéen ts'o'ojke' ka tsajik.",
      "dependents": [
        {
          "tier": "T2",
          "values": [
            {
              "start_slot": 0,
              "end_slot": 1,
              "value": "chéen ts'o'ojke' ka tsajik."
            }
          ]
        },
        {
          "tier": "T3",
          "values": [
            {
              "start_slot": 0,
              "end_slot": 1,
              "value": "después lo fríes."
            }
          ]
        }
      ]
    },
    {
      "speaker": "S1",
      "tier": "T1",
      "start_time_ms": 265990,
      "end_time_ms": 267495,
      "num_slots": 1,
      "text": "Esten... chéen ts'o'okok túun beyo'",
      "dependents": [
        {
          "tier": "T2",
          "values": [
            {
              "start_slot": 0,
              "end_slot": 1,
              "value": "Esten... chéen ts'o'okok túun beyo'"
            }
          ]
        },
        {
          "tier": "T3",
          "values": [
            {
              "start_slot": 0,
              "end_slot": 1,
              "value": "Esten... después así entonces"
            }
          ]
        }
      ]
    },
    {
      "speaker": "S1",
      "tier": "T1",
      "start_time_ms": 268265,
      "end_time_ms": 270070,
      "num_slots": 1,
      "text": "chéen ts'o'okok tun beye k'óol beyo'",
      "dependents": [
        {
          "tier": "T2",
          "values": [
            {
              "start_slot": 0,
              "end_slot": 1,
              "value": "chéen ts'o'okok tun bey le k'óol beyo'"
            }
          ]
        },
        {
          "tier": "T3",
          "values": [
            {
              "start_slot": 0,
              "end_slot": 1,
              "value": "después del entonces así el k'óol así"
            }
          ]
        }
      ]
    },
    {
      "speaker": "S1",
      "tier": "T1",
      "start_time_ms": 271290,
      "end_time_ms": 273060,
      "num_slots": 1,
      "text": "ka estenala a... a...",
      "dependents": [
        {
          "tier": "T2",
          "values": [
            {
              "start_slot": 0,
              "end_slot": 1,
              "value": "ka estenala a... a..."
            }
          ]
        },
        {
          "tier": "T3",
          "values": [
            {
              "start_slot": 0,
              "end_slot": 1,
              "value": "lo esten lo... lo..."
            }
          ]
        }
      ]
    },
    {
      "speaker": "S1",
      "tier": "T1",
      "start_time_ms": 274585,
      "end_time_ms": 277265,
      "num_slots": 1,
      "text": "e jkaaxo' yana báanyartik yéetel xa'ak'",
      "dependents": [
        {
          "tier": "T2",
          "values": [
            {
              "start_slot": 0,
              "end_slot": 1,
              "value": "le jkaaxo' yaan a báanyartik yéetel xa'ak'"
            }
          ]
        },
        {
          "tier": "T3",
          "values": [
            {
              "start_slot": 0,
              "end_slot": 1,
              "value": "el pollo lo vas a bañar con recado"
            }
          ]
        }
      ]
    },
    {
      "speaker": "S1",
      "tier": "T1",
      "start_time_ms": 277275,
      "end_time_ms": 279365,
      "num_slots": 1,
      "text": "yetu p'íit. p'íit náaranja",
      "dependents": [
        {
          "tier": "T2",
          "values": [
            {
              "start_slot": 0,
              "end_slot": 1,
              "value": "yéetel jump'íit, jump'íit náaranja"
            }
          ]
        },
        {
          "tier": "T3",
          "values": [
            {
              "start_slot": 0,
              "end_slot": 1,
              "value": "con un poco, un poco de naranja"
            }
          ]
        }
      ]
    },
    {
      "speaker": "S1",
      "tier": "T1",
      "start_time_ms": 280205,
      "end_time_ms": 281650,
      "num_slots": 1,
      "text": "chéen ts'o'ojke' ka k'a'atik",
      "dependents": [
        {
          "tier": "T2",
          "values": [
            {
              "start_slot": 0,
              "end_slot": 1,
              "value": "chéen ts'o'ojke' ka k'a'atik"
            }
          ]
        },
        {
          "tier": "T3",
          "values": [
            {
              "start_slot": 0,
              "end_slot": 1,
              "value": "después lo asas"
            }
          ]
        }
      ]
    },
    {
      "speaker": "S1",
      "tier": "T1",
      "start_time_ms": 282240,
      "end_time_ms": 284065,
      "num_slots": 1,
      "text": "chéen ts'o'okok túun beyu k'a'achajlo'",
      "dependents": [
        {
          "tier": "T2",
          "values": [
            {
              "start_slot": 0,
              "end_slot": 1,
              "value": "chéen ts'o'okok túun bey u k'a'achajlo'"
            }
          ]
        },
        {
          "tier": "T3",
          "values": [
            {
              "start_slot": 0,
              "end_slot": 1,
              "value": "después de que se ase así entonces"
            }
          ]
        }
      ]
    },
    {
      "speaker": "S1",
      "tier": "T1",
      "start_time_ms": 284660,
      "end_time_ms": 285980,
      "num_slots": 1,
      "text": "ku tsi'ikta'a túun",
      "dependents": [
        {
          "tier": "T2",
          "values": [
            {
              "start_slot": 0,
              "end_slot": 1,
              "value": "ku tsi'ikta'al túun"
            }
          ]
        },
        {
          "tier": "T3",
          "values": [
            {
              "start_slot": 0,
              "end_slot": 1,
              "value": "se desmenuza entonces"
            }
          ]
        }
      ]
    },
    {
      "speaker": "S1",
      "tier": "T1",
      "start_time_ms": 286505,
      "end_time_ms": 288805,
      "num_slots": 1,
      "text": "chéen ts'o'ojke ku ts'áabal te' ichile e...",
      "dependents": [
        {
          "tier": "T2",
          "values": [
            {
              "start_slot": 0,
              "end_slot": 1,
              "value": "chéen ts'o'ojke ku ts'áabal te' ichile e..."
            }
          ]
        },
        {
          "tier": "T3",
          "values": [
            {
              "start_slot": 0,
              "end_slot": 1,
              "value": "después se pone dentro del... del.."
            }
          ]
        }
      ]
    },
    {
      "speaker": "S1",
      "tier": "T1",
      "start_time_ms": 289940,
      "end_time_ms": 291015,
      "num_slots": 1,
      "text": "e k'óolo'",
      "dependents": [
        {
          "tier": "T2",
          "values": [
            {
              "start_slot": 0,
              "end_slot": 1,
              "value": "le k'óolo'"
            }
          ]
        },
        {
          "tier": "T3",
          "values": [
            {
              "start_slot": 0,
              "end_slot": 1,
              "value": "del k'óol"
            }
          ]
        }
      ]
    }
  ]
}